avmesos_airflow_provider/__init__.py
avmesos_airflow_provider/executors/__init__.py
avmesos_airflow_provider/executors/mesos_executor.py
avmesos_airflow_provider/operators/__init__.py
avmesos_airflow_provider/operators/mesos.py
avmesos_airflow_provider-0.3.1.dist-info/METADATA
avmesos_airflow_provider-0.3.1.dist-info/WHEEL
avmesos_airflow_provider-0.3.1.dist-info/top_level.txt
avmesos_airflow_provider-0.3.1.dist-info/RECORD
