Metadata-Version: 2.4
Name: avmesos_airflow_provider
Version: 0.3.1
Summary: Apache Mesos Provider
Home-page: https://www.aventer.biz/
Author: Andreas Peters
Author-email: support@aventer.biz
License: Apache License 2.0
Requires-Python: >=3.6
Requires-Dist: apache-airflow>=2.0
Requires-Dist: avmesos>=0.4.2
Requires-Dist: waitress
Requires-Dist: flask_httpauth
Requires-Dist: prometheus-client
Dynamic: author
Dynamic: author-email
Dynamic: description
Dynamic: description-content-type
Dynamic: home-page
Dynamic: license
Dynamic: requires-dist
Dynamic: requires-python
Dynamic: summary
